vagquery/__init__.py
vagquery/departure.py
vagquery/station.py
vagquery-1.2.dist-info/WHEEL
vagquery-1.2.dist-info/METADATA
vagquery-1.2.dist-info/RECORD
