Metadata-Version: 2.1
Name: vagquery
Version: 1.2
Summary: Queries for VAG public transportation time schedules
Home-page: https://github.com/derphilipp/vagquery
License: MIT
Keywords: vag,public,transport
Author: Philipp Weißmann
Author-email: mail@philipp-weissmann.de
Requires-Python: >=3.7,<4.0
Classifier: License :: OSI Approved :: MIT License
Classifier: Programming Language :: Python :: 3
Classifier: Programming Language :: Python :: 3.7
Classifier: Programming Language :: Python :: 3.8
Classifier: Programming Language :: Python :: 3.9
Requires-Dist: pytz (>=2018.07,<2019.0)
Requires-Dist: requests (>=2.18.4,<3.0.0)
Project-URL: Repository, https://github.com/derphilipp/vagquery
